README.rst
setup.py
confluence_command_line.egg-info/PKG-INFO
confluence_command_line.egg-info/SOURCES.txt
confluence_command_line.egg-info/dependency_links.txt
confluence_command_line.egg-info/entry_points.txt
confluence_command_line.egg-info/requires.txt
confluence_command_line.egg-info/top_level.txt
confluencecommandline/__init__.py
confluencecommandline/confluence_command_line.py
confluencecommandline/util.py
confluencecommandline/commands/__init__.py
confluencecommandline/commands/create_skeleton.py