Metadata-Version: 1.0
Name: confluence-command-line
Version: 0.4
Summary: Confluence Command Line (ccl) is a suite of command line utilities designed to make working with confluence faster and easier. 
Home-page: https://github.com/jsinglet/confluence-command-line
Author: John L. Singleton
Author-email: jsinglet@gmail.com
License: MIT
Platform: UNKNOWN
